src/__init__.py
src/main.py
src/prompts/__init__.py
src/prompts/appunti.py
src/prompts/hacker.py
src/prompts/math.py
src/prompts/python_coder.py
src/prompts/rust_coder.py
src/prompts/summerizer.py
src/prompts/uncensored_assistant.py
orchestrator.ai-2.0.dist-info/METADATA
orchestrator.ai-2.0.dist-info/WHEEL
orchestrator.ai-2.0.dist-info/entry_points.txt
orchestrator.ai-2.0.dist-info/top_level.txt
orchestrator.ai-2.0.dist-info/RECORD
