Metadata-Version: 2.1
Name: orchestrator.ai
Version: 2.0
Summary: Semplice gestore di agenti ai/assistenti scritto in python per uso personale. Permette di usare numerosi modelli tramite le api gratuite di sambanova.ai, mistral.ai, openrouter.ai e github.com specializzati in determinati compiti tramite appositi prompt.
Home-page: https://github.com/CiroBurro/orchestrator-ai
Author: Filippo Baglioni
Author-email: filobaglioni.06@gmail.com
Classifier: Programming Language :: Python :: 3
Classifier: License :: OSI Approved :: MIT License
Classifier: Operating System :: OS Independent
Requires-Python: >=3.6
Requires-Dist: openai
Requires-Dist: python-dotenv
